{
  "info": {
    "_postman_id": "d20c2d1f-f749-420e-a1d2-78a13709be40",
    "name": "task-management-api",
    "schema": "https://schema.getpostman.com/json/collection/v2.1.0/collection.json",
    "_exporter_id": "55811656",
    "_collection_link": "https://go.postman.co/collection/55811656-d20c2d1f-f749-420e-a1d2-78a13709be40?source=collection_link"
  },
  "item": [
    {
      "name": "Register",
      "request": {
        "method": "POST",
        "header": [],
        "body": {
          "mode": "raw",
          "raw": "{\r\n    \"name\" : \"user normal\", \r\n    \"email\" : \"usernormal@gmail.com\",\r\n    \"password\": \"usernormal\"\r\n}",
          "options": {
            "raw": {
              "language": "json"
            }
          }
        },
        "url": {
          "raw": "{{BaseURL}}/api/auth/register",
          "host": [
            "{{BaseURL}}"
          ],
          "path": [
            "api",
            "auth",
            "register"
          ]
        }
      },
      "response": []
    },
    {
      "name": "Login as User",
      "request": {
        "method": "POST",
        "header": [],
        "body": {
          "mode": "raw",
          "raw": "{\r\n    \"email\" : \"admin@gmail.com\",\r\n    \"password\": \"123456\"\r\n}",
          "options": {
            "raw": {
              "language": "json"
            }
          }
        },
        "url": {
          "raw": "{{BaseURL}}/api/auth/login",
          "host": [
            "{{BaseURL}}"
          ],
          "path": [
            "api",
            "auth",
            "login"
          ]
        }
      },
      "response": []
    },
    {
      "name": "Login as Admin",
      "request": {
        "method": "POST",
        "header": [],
        "body": {
          "mode": "raw",
          "raw": "{\r\n    \"email\" : \"admin@gmail.com\",\r\n    \"password\": \"123456\"\r\n}",
          "options": {
            "raw": {
              "language": "json"
            }
          }
        },
        "url": {
          "raw": "{{BaseURL}}/api/auth/login",
          "host": [
            "{{BaseURL}}"
          ],
          "path": [
            "api",
            "auth",
            "login"
          ]
        }
      },
      "response": []
    },
    {
      "name": "User - Get Own Data",
      "request": {
        "method": "GET",
        "header": [
          {
            "key": "Authorization",
            "value": "{{bearer_token_1ag1}}",
            "type": "text"
          }
        ],
        "url": {
          "raw": "{{BaseURL}}/api/auth/me",
          "host": [
            "{{BaseURL}}"
          ],
          "path": [
            "api",
            "auth",
            "me"
          ]
        }
      },
      "response": []
    },
    {
      "name": "Project - Create",
      "request": {
        "method": "POST",
        "header": [
          {
            "key": "Authorization",
            "value": "{{bearer_token_0kpa}}",
            "type": "text"
          }
        ],
        "body": {
          "mode": "raw",
          "raw": "{\r\n    \"name\" : \"project 6\",\r\n    \"description\" : \"description 6\"\r\n}",
          "options": {
            "raw": {
              "language": "json"
            }
          }
        },
        "url": {
          "raw": "{{BaseURL}}/api/projects",
          "host": [
            "{{BaseURL}}"
          ],
          "path": [
            "api",
            "projects"
          ]
        }
      },
      "response": []
    },
    {
      "name": "Project - Update",
      "request": {
        "method": "PUT",
        "header": [
          {
            "key": "Authorization",
            "value": "{{bearer_token_0kpa}}",
            "type": "text"
          }
        ],
        "body": {
          "mode": "raw",
          "raw": "{\r\n    \"name\" : \"project 6 update\",\r\n    \"description\" : \"description 6 update\"\r\n}",
          "options": {
            "raw": {
              "language": "json"
            }
          }
        },
        "url": {
          "raw": "{{BaseURL}}/api/projects/6",
          "host": [
            "{{BaseURL}}"
          ],
          "path": [
            "api",
            "projects",
            "6"
          ]
        }
      },
      "response": []
    },
    {
      "name": "Project - Get All",
      "protocolProfileBehavior": {
        "disableBodyPruning": true
      },
      "request": {
        "method": "GET",
        "header": [
          {
            "key": "Authorization",
            "value": "{{bearer_token_0kpa}}",
            "type": "text"
          }
        ],
        "body": {
          "mode": "raw",
          "raw": "",
          "options": {
            "raw": {
              "language": "json"
            }
          }
        },
        "url": {
          "raw": "{{BaseURL}}/api/projects",
          "host": [
            "{{BaseURL}}"
          ],
          "path": [
            "api",
            "projects"
          ]
        }
      },
      "response": []
    },
    {
      "name": "Project - Get By ID",
      "protocolProfileBehavior": {
        "disableBodyPruning": true
      },
      "request": {
        "method": "GET",
        "header": [
          {
            "key": "Authorization",
            "value": "{{bearer_token_0yzj}}",
            "type": "text"
          }
        ],
        "body": {
          "mode": "raw",
          "raw": "",
          "options": {
            "raw": {
              "language": "json"
            }
          }
        },
        "url": {
          "raw": "{{BaseURL}}/api/projects/5",
          "host": [
            "{{BaseURL}}"
          ],
          "path": [
            "api",
            "projects",
            "5"
          ]
        }
      },
      "response": []
    },
    {
      "name": "Project - Delete",
      "request": {
        "method": "DELETE",
        "header": [
          {
            "key": "Authorization",
            "value": "{{bearer_token_0yzj}}",
            "type": "text"
          }
        ],
        "body": {
          "mode": "raw",
          "raw": "",
          "options": {
            "raw": {
              "language": "json"
            }
          }
        },
        "url": {
          "raw": "{{BaseURL}}/api/projects/6",
          "host": [
            "{{BaseURL}}"
          ],
          "path": [
            "api",
            "projects",
            "6"
          ]
        }
      },
      "response": []
    },
    {
      "name": "Project - Get task By project",
      "protocolProfileBehavior": {
        "disableBodyPruning": true
      },
      "request": {
        "method": "GET",
        "header": [
          {
            "key": "Authorization",
            "value": "{{bearer_token_0yzj}}",
            "type": "text"
          }
        ],
        "body": {
          "mode": "raw",
          "raw": "",
          "options": {
            "raw": {
              "language": "json"
            }
          }
        },
        "url": {
          "raw": "{{BaseURL}}/api/projects/4/tasks",
          "host": [
            "{{BaseURL}}"
          ],
          "path": [
            "api",
            "projects",
            "4",
            "tasks"
          ]
        }
      },
      "response": []
    },
    {
      "name": "AI - Prompt test case 1",
      "request": {
        "method": "POST",
        "header": [
          {
            "key": "Authorization",
            "value": "{{bearer_token_0kpa}}",
            "type": "text"
          }
        ],
        "body": {
          "mode": "raw",
          "raw": "{\r\n    \"prompt\" : \"kasih tugas migrasi db pada project id 4 ke user id 1 low dengan judul migrasi db dan deskripsi segera dikerjakan\"\r\n}",
          "options": {
            "raw": {
              "language": "json"
            }
          }
        },
        "url": {
          "raw": "{{BaseURL}}/api/ai/command",
          "host": [
            "{{BaseURL}}"
          ],
          "path": [
            "api",
            "ai",
            "command"
          ]
        }
      },
      "response": []
    },
    {
      "name": "AI - Prompt test case 2",
      "request": {
        "method": "POST",
        "header": [
          {
            "key": "Authorization",
            "value": "{{bearer_token_0kpa}}",
            "type": "text"
          }
        ],
        "body": {
          "mode": "raw",
          "raw": "{\r\n    \"prompt\" : \"Update task ID 25 jadi selesai.\"\r\n}",
          "options": {
            "raw": {
              "language": "json"
            }
          }
        },
        "url": {
          "raw": "{{BaseURL}}/api/ai/command",
          "host": [
            "{{BaseURL}}"
          ],
          "path": [
            "api",
            "ai",
            "command"
          ]
        }
      },
      "response": []
    },
    {
      "name": "AI - Prompt test case 3",
      "request": {
        "method": "POST",
        "header": [
          {
            "key": "Authorization",
            "value": "{{bearer_token_0kpa}}",
            "type": "text"
          }
        ],
        "body": {
          "mode": "raw",
          "raw": "{\r\n    \"prompt\" : \"Buatkan tugas buat dokumentasi laporan ci/cd pada project 4 ke user 2 dengan judul laporan dokuemntasi dan deskripsi segera dikerjakan, kemudian selesai task 24\"\r\n}",
          "options": {
            "raw": {
              "language": "json"
            }
          }
        },
        "url": {
          "raw": "{{BaseURL}}/api/ai/command",
          "host": [
            "{{BaseURL}}"
          ],
          "path": [
            "api",
            "ai",
            "command"
          ]
        }
      },
      "response": []
    },
    {
      "name": "AI - Prompt test case 4",
      "request": {
        "method": "POST",
        "header": [
          {
            "key": "Authorization",
            "value": "{{bearer_token_0kpa}}",
            "type": "text"
          }
        ],
        "body": {
          "mode": "raw",
          "raw": "{\r\n    \"prompt\" : \"Buatkan task print dokumentasi laporan ci/cd pada project 4 ke user 2 dengan judul print laporan dokuemntasi dan deskripsi segera dikerjakan, kemudian ubah task 25 menjadi sedang dikerjakan, dan buat task makan makan pada project 6 ke user 2 dengan judul makan makan dengan deskripsi rencana makan-makan akhir tahun\"\r\n}",
          "options": {
            "raw": {
              "language": "json"
            }
          }
        },
        "url": {
          "raw": "{{BaseURL}}/api/ai/command",
          "host": [
            "{{BaseURL}}"
          ],
          "path": [
            "api",
            "ai",
            "command"
          ]
        }
      },
      "response": []
    },
    {
      "name": "AI - Prompt test case 5",
      "request": {
        "method": "POST",
        "header": [
          {
            "key": "Authorization",
            "value": "{{bearer_token_0kpa}}",
            "type": "text"
          }
        ],
        "body": {
          "mode": "raw",
          "raw": "{\r\n    \"prompt\" : \"Tampilkan semua projects yang sedang high?\"\r\n}",
          "options": {
            "raw": {
              "language": "json"
            }
          }
        },
        "url": {
          "raw": "{{BaseURL}}/api/ai/command",
          "host": [
            "{{BaseURL}}"
          ],
          "path": [
            "api",
            "ai",
            "command"
          ]
        }
      },
      "response": []
    },
    {
      "name": "AI - Prompt test case 6",
      "request": {
        "method": "POST",
        "header": [
          {
            "key": "Authorization",
            "value": "{{bearer_token_0kpa}}",
            "type": "text"
          }
        ],
        "body": {
          "mode": "raw",
          "raw": "{\r\n    \"prompt\" : \"Apa saja project yang sedang dikerjakan user 2\"\r\n}",
          "options": {
            "raw": {
              "language": "json"
            }
          }
        },
        "url": {
          "raw": "{{BaseURL}}/api/ai/command",
          "host": [
            "{{BaseURL}}"
          ],
          "path": [
            "api",
            "ai",
            "command"
          ]
        }
      },
      "response": []
    }
  ],
  "event": [
    {
      "listen": "prerequest",
      "script": {
        "type": "text/javascript",
        "packages": {},
        "requests": {},
        "exec": [
          ""
        ]
      }
    },
    {
      "listen": "test",
      "script": {
        "type": "text/javascript",
        "packages": {},
        "requests": {},
        "exec": [
          ""
        ]
      }
    }
  ],
  "variable": [
    {
      "key": "bearer_token_0kpa",
      "secret": true
    },
    {
      "key": "bearer_token_0yzj",
      "secret": true
    },
    {
      "key": "bearer_token_1ag1",
      "secret": true
    },
    {
      "key": "supabase_service_role_api_key_0adt",
      "secret": true
    },
    {
      "key": "supabase_service_role_api_key_0jg0",
      "secret": true
    },
    {
      "key": "supabase_service_role_api_key_0wrj",
      "secret": true
    }
  ]
}